hpr_scratcher/__init__.py
hpr_scratcher-0.6.1.dist-info/METADATA
hpr_scratcher-0.6.1.dist-info/WHEEL
hpr_scratcher-0.6.1.dist-info/entry_points.txt
hpr_scratcher-0.6.1.dist-info/RECORD
