Metadata-Version: 2.1
Name: hpr-scratcher
Version: 0.6.1
Summary: A scratchpad manager for hyprland
Home-page: https://github.com/hyprland-community/hpr-scratcher
License: MIT
Author: fdev31
Author-email: fdev31@gmail.com
Requires-Python: >=3.10,<4.0
Classifier: License :: OSI Approved :: MIT License
Classifier: Programming Language :: Python :: 3
Classifier: Programming Language :: Python :: 3.10
Classifier: Programming Language :: Python :: 3.11
